{
  "openapi": "3.0.1",
  "info": {
    "title": "班级信息中心云平台JavaAPI",
    "description": "",
    "version": "1.0.0"
  },
  "tags": [
    {
      "name": "抽号接口"
    },
    {
      "name": "成绩管理"
    }
  ],
  "paths": {
    "/api/random": {
      "get": {
        "summary": "获取抽号列表",
        "deprecated": false,
        "description": "",
        "operationId": "getRandomList",
        "tags": [
          "抽号接口"
        ],
        "parameters": [
          {
            "name": "X-Token",
            "in": "header",
            "description": "令牌Token",
            "required": false,
            "example": "",
            "schema": {
              "type": "string"
            }
          }
        ],
        "responses": {
          "200": {
            "description": "",
            "content": {
              "application/json": {
                "schema": {
                  "$ref": "#/components/schemas/Result"
                }
              }
            },
            "headers": {}
          }
        },
        "security": []
      }
    },
    "/api/exams": {
      "get": {
        "summary": "获取考试列表",
        "deprecated": false,
        "description": "",
        "operationId": "getExamList",
        "tags": [
          "成绩管理"
        ],
        "parameters": [
          {
            "name": "X-Token",
            "in": "header",
            "description": "令牌Token",
            "required": false,
            "example": "",
            "schema": {
              "type": "string"
            }
          }
        ],
        "responses": {
          "200": {
            "description": "",
            "content": {
              "application/json": {
                "schema": {
                  "$ref": "#/components/schemas/Result"
                }
              }
            },
            "headers": {}
          }
        },
        "security": []
      }
    },
    "/api/exams/{id}": {
      "get": {
        "summary": "获取考试报告",
        "deprecated": false,
        "description": "",
        "operationId": "getExamReport",
        "tags": [
          "成绩管理"
        ],
        "parameters": [
          {
            "name": "id",
            "in": "path",
            "description": "",
            "required": true,
            "example": 0,
            "schema": {
              "type": "integer",
              "format": "int32"
            }
          },
          {
            "name": "X-Token",
            "in": "header",
            "description": "令牌Token",
            "required": false,
            "example": "",
            "schema": {
              "type": "string"
            }
          }
        ],
        "responses": {
          "200": {
            "description": "",
            "content": {
              "application/json": {
                "schema": {
                  "$ref": "#/components/schemas/Result"
                }
              }
            },
            "headers": {}
          }
        },
        "security": []
      }
    }
  },
  "components": {
    "schemas": {
      "Result": {
        "type": "object",
        "properties": {
          "code": {
            "type": "integer",
            "format": "int32"
          },
          "msg": {
            "type": "string"
          },
          "data": {
            "type": "object",
            "properties": {}
          }
        }
      }
    },
    "securitySchemes": {}
  },
  "servers": [],
  "security": []
}